hishel/__init__.py
hishel/_async_cache.py
hishel/_async_httpx.py
hishel/_policies.py
hishel/_sync_cache.py
hishel/_sync_httpx.py
hishel/_utils.py
hishel/asgi.py
hishel/fastapi.py
hishel/httpx.py
hishel/py.typed
hishel/requests.py
hishel/_core/_headers.py
hishel/_core/_spec.py
hishel/_core/models.py
hishel/_core/_storages/_async_base.py
hishel/_core/_storages/_async_sqlite.py
hishel/_core/_storages/_packing.py
hishel/_core/_storages/_sync_base.py
hishel/_core/_storages/_sync_sqlite.py
hishel-1.1.6.dist-info/METADATA
hishel-1.1.6.dist-info/WHEEL
hishel-1.1.6.dist-info/licenses/LICENSE
hishel-1.1.6.dist-info/RECORD
